CHANGELOG
MANIFEST.in
README.rst
setup.cfg
setup.py
versioneer.py
bin/dtram.py
bin/xtram.py
ext/dtram/_dtram.c
ext/dtram/_dtram.h
ext/dtram/dtram.pyx
ext/lse/_lse.c
ext/lse/_lse.h
ext/lse/lse.pyx
ext/xtram/_xtram.c
ext/xtram/_xtram.h
ext/xtram/xtram.pyx
pytram/__init__.py
pytram/_version.py
pytram/api.py
pytram/estimator.py
pytram/reader.py
pytram/tramdata.py
pytram.egg-info/PKG-INFO
pytram.egg-info/SOURCES.txt
pytram.egg-info/dependency_links.txt
pytram.egg-info/requires.txt
pytram.egg-info/top_level.txt
pytram/_dtram/__init__.py
pytram/_dtram/dtram.py
pytram/_xtram/__init__.py
pytram/_xtram/xtram.py
test/test_dtram.py
test/test_estimator.py
test/test_exceptions.py
test/test_lse.py
test/test_three_state_model.py
test/test_tramdata.py
test/test_xtram.py