Metadata-Version: 1.1
Name: pytram
Version: 0.2.4
Summary: The TRAM package
Home-page: https://github.com/markovmodel/pytram
Author: The pytram team
Author-email: pytram@lists.fu-berlin.de
License: Simplified BSD License
Keywords: free energy,Markov state model,TRAM,dTRAM,xTRAM
Platform: UNKNOWN
Classifier: Development Status :: 4 - Beta
Classifier: Environment :: Console
Classifier: Intended Audience :: Science/Research
Classifier: License :: OSI Approved :: BSD License
Classifier: Natural Language :: English
Classifier: Operating System :: MacOS :: MacOS X
Classifier: Operating System :: POSIX :: Linux
Classifier: Programming Language :: C
Classifier: Programming Language :: Cython
Classifier: Programming Language :: Python :: 2.7
Classifier: Topic :: Scientific/Engineering :: Bio-Informatics
Classifier: Topic :: Scientific/Engineering :: Chemistry
Classifier: Topic :: Scientific/Engineering :: Mathematics
Classifier: Topic :: Scientific/Engineering :: Physics
